shortpath83/README.MD
shortpath83/__init__.py
shortpath83/requirements.txt
shortpath83/thirdparty.json
shortpath83-0.12.dist-info/LICENSE.rst
shortpath83-0.12.dist-info/METADATA
shortpath83-0.12.dist-info/WHEEL
shortpath83-0.12.dist-info/top_level.txt
shortpath83-0.12.dist-info/RECORD
