Metadata-Version: 2.1
Name: shortpath83
Version: 0.12
Summary: simplifies Windows path handling, providing short path name conversion and string path manipulation
Home-page: https://github.com/hansalemaos/shortpath83
Author: Johannes Fischer
Author-email: aulasparticularesdealemaosp@gmail.com
License: MIT
Keywords: windows,subprocess,83,short names
Classifier: Development Status :: 4 - Beta
Classifier: Programming Language :: Python :: 3 :: Only
Classifier: Programming Language :: Python :: 3.10
Classifier: Topic :: Software Development :: Libraries :: Python Modules
Classifier: Topic :: Utilities
License-File: LICENSE.rst
